windrow/__about__.py
windrow/__init__.py
windrow/__main__.py
windrow/app.py
windrow/config.py
windrow/nodes/__init__.py
windrow/nodes/test_accumulate.py
windrow/nodes/test_add_value.py
windrow/nodes/test_below.py
windrow/nodes/test_double.py
windrow/nodes/test_greet.py
windrow/nodes/test_merge.py
windrow/nodes/test_remainder.py
windrow/nodes/test_rename.py
windrow/nodes/test_repeat.py
windrow/nodes/test_subtract.py
windrow/nodes/test_sum.py
windrow/pipelines/default.yml
windrow/routers/__init__.py
windrow/routers/pipelines.py
windrow-0.0.1rc0.dist-info/METADATA
windrow-0.0.1rc0.dist-info/WHEEL
windrow-0.0.1rc0.dist-info/licenses/LICENSE
windrow-0.0.1rc0.dist-info/RECORD
